django_lightweight_queue/__init__.py
django_lightweight_queue/app_settings.py
django_lightweight_queue/apps.py
django_lightweight_queue/backends/__init__.py
django_lightweight_queue/backends/base.py
django_lightweight_queue/backends/debug_web.py
django_lightweight_queue/backends/redis.py
django_lightweight_queue/backends/reliable_redis.py
django_lightweight_queue/backends/synchronous.py
django_lightweight_queue/command_utils.py
django_lightweight_queue/constants.py
django_lightweight_queue/cron_scheduler.py
django_lightweight_queue/exposition.py
django_lightweight_queue/job.py
django_lightweight_queue/machine_types.py
django_lightweight_queue/management/__init__.py
django_lightweight_queue/management/commands/__init__.py
django_lightweight_queue/management/commands/queue_clear.py
django_lightweight_queue/management/commands/queue_configuration.py
django_lightweight_queue/management/commands/queue_deduplicate.py
django_lightweight_queue/management/commands/queue_pause.py
django_lightweight_queue/management/commands/queue_resume.py
django_lightweight_queue/management/commands/queue_runner.py
django_lightweight_queue/management/commands/queue_worker.py
django_lightweight_queue/middleware/__init__.py
django_lightweight_queue/middleware/logging.py
django_lightweight_queue/progress_logger.py
django_lightweight_queue/py.typed
django_lightweight_queue/runner.py
django_lightweight_queue/task.py
django_lightweight_queue/types.py
django_lightweight_queue/urls.py
django_lightweight_queue/utils.py
django_lightweight_queue/views.py
django_lightweight_queue/worker.py
django_lightweight_queue-4.11.0.dist-info/COPYING
django_lightweight_queue-4.11.0.dist-info/WHEEL
django_lightweight_queue-4.11.0.dist-info/METADATA
django_lightweight_queue-4.11.0.dist-info/RECORD
