Metadata-Version: 2.1
Name: django-lightweight-queue
Version: 4.11.0
Summary: Lightweight & modular queue and cron system for Django
Home-page: https://github.com/thread/django-lightweight-queue/
License: BSD-3-Clause
Author: Thread Engineering
Author-email: tech@thread.com
Requires-Python: >=3.6.1,<4
Classifier: Development Status :: 5 - Production/Stable
Classifier: Framework :: Django
Classifier: License :: OSI Approved :: BSD License
Classifier: Programming Language :: Python :: 3
Classifier: Programming Language :: Python :: 3.10
Classifier: Programming Language :: Python :: 3.7
Classifier: Programming Language :: Python :: 3.8
Classifier: Programming Language :: Python :: 3.9
Provides-Extra: progress
Provides-Extra: redis
Requires-Dist: daemonize (>=2.5.0,<2.6.0)
Requires-Dist: django (>=2.2)
Requires-Dist: prometheus-client (>=0.7,<1.0)
Requires-Dist: redis; extra == "redis"
Requires-Dist: tqdm (>=4.54.1,<5.0.0); extra == "progress"
Requires-Dist: typing-extensions (>=4,<5)
